CHANGES.txt
MANIFEST.in
README.md
setup.cfg
setup.py
penelope/__init__.py
penelope.trac.egg-info/PKG-INFO
penelope.trac.egg-info/SOURCES.txt
penelope.trac.egg-info/dependency_links.txt
penelope.trac.egg-info/entry_points.txt
penelope.trac.egg-info/namespace_packages.txt
penelope.trac.egg-info/not-zip-safe
penelope.trac.egg-info/requires.txt
penelope.trac.egg-info/top_level.txt
penelope/trac/__init__.py
penelope/trac/auth_wsgi.py
penelope/trac/authz.py
penelope/trac/communication.py
penelope/trac/events.py
penelope/trac/i18n.py
penelope/trac/monkey.py
penelope/trac/plugins.py
penelope/trac/populate.py
penelope/trac/trac-rescope.py
penelope/trac/user.py
penelope/trac/workflow.py
penelope/trac/htdocs/por.css
penelope/trac/htdocs/por.js
penelope/trac/htdocs/rescoped-css/about.css
penelope/trac/htdocs/rescoped-css/admin.css
penelope/trac/htdocs/rescoped-css/browser.css
penelope/trac/htdocs/rescoped-css/changeset.css
penelope/trac/htdocs/rescoped-css/code.css
penelope/trac/htdocs/rescoped-css/diff.css
penelope/trac/htdocs/rescoped-css/prefs.css
penelope/trac/htdocs/rescoped-css/report.css
penelope/trac/htdocs/rescoped-css/roadmap.css
penelope/trac/htdocs/rescoped-css/search.css
penelope/trac/htdocs/rescoped-css/ticket.css
penelope/trac/htdocs/rescoped-css/timeline.css
penelope/trac/htdocs/rescoped-css/trac.css
penelope/trac/htdocs/rescoped-css/wiki.css
penelope/trac/locale/messages.pot
penelope/trac/locale/en/LC_MESSAGES/trac.por.po
penelope/trac/locale/it/LC_MESSAGES/trac.por.po
penelope/trac/templates/admin-communication.html
penelope/trac/templates/por_theme.html
penelope/trac/tests/__init__.py
penelope/trac/tests/test_notification.py