Metadata-Version: 1.1
Name: penelope.trac
Version: 1.2.4
Summary: Penelope: Trac integration
Home-page: http://getpenelope.github.com
Author: Penelope Team
Author-email: penelopedev@redturtle.it
License: UNKNOWN
Keywords: web wsgi bfg pylons pyramid
Platform: UNKNOWN
Classifier: Programming Language :: Python
Classifier: Framework :: Pylons
